Frequent_Pattern/Apriori.py
Frequent_Pattern/ECLAT.py
Frequent_Pattern/FPGrowth.py
Frequent_Pattern/__init__.py
Frequent_Pattern/abstract.py
fpmine-1.0.2.dist-info/METADATA
fpmine-1.0.2.dist-info/WHEEL
fpmine-1.0.2.dist-info/top_level.txt
fpmine-1.0.2.dist-info/RECORD
