Metadata-Version: 2.4
Name: fpmine
Version: 1.0.2
Summary: Frequent Pattern Mining Algorithms
Home-page: https://github.com/lokeshreddyayyaswamy/Pattern_Mining
Author: Lokesh A
Author-email: lokeshreddy2680@gmail.com
Classifier: Programming Language :: Python :: 3
Classifier: Operating System :: OS Independent
Requires-Python: >=3.6
Requires-Dist: numpy
Requires-Dist: urllib3
Requires-Dist: validators
Requires-Dist: sphinx
Requires-Dist: sphinx-rtd-theme
Requires-Dist: pandas
Requires-Dist: validators
Requires-Dist: psutil
Dynamic: author
Dynamic: author-email
Dynamic: classifier
Dynamic: description
Dynamic: description-content-type
Dynamic: home-page
Dynamic: requires-dist
Dynamic: requires-python
Dynamic: summary
